{
  "format_version": "1.8.0",
  "minecraft:spawn_rules": {
    "description": {
      "identifier": "sf_nba:crab",
      "population_control": "animal"
    },
    "conditions": [
      {
        "minecraft:spawns_on_surface": {},
        "minecraft:spawns_underwater": {},
        "minecraft:weight": {
          "default": 20
        },
        "minecraft:herd": {
          "min_size": 1,
          "max_size": 3
        },
        "minecraft:biome_filter": {
          "any_of": [
            {
              "test": "has_biome_tag",
              "operator": "==",
              "value": "beach"
            },
            {
              "test": "has_biome_tag",
              "operator": "==",
              "value": "frozen"
            },
            {
              "test": "has_biome_tag",
              "operator": "==",
              "value": "ocean"
            },
            {
              "test": "has_biome_tag",
              "operator": "==",
              "value": "frozen_ocean"
            }
          ]
        }
      }
    ]
  }
}